{
  "main": {
    "id": "1a9f26ef2db0c80d",
    "type": "split",
    "children": [
      {
        "id": "8527837003231952",
        "type": "tabs",
        "children": [
          {
            "id": "99f0df813e2a4513",
            "type": "leaf",
            "state": {
              "type": "notification-dashboard-view",
              "state": {}
            }
          }
        ]
      }
    ],
    "direction": "vertical"
  },
  "left": {
    "id": "7180a25840f775fe",
    "type": "split",
    "children": [
      {
        "id": "3aed828a1a32e70d",
        "type": "tabs",
        "children": [
          {
            "id": "0e70ac006bb0b5f4",
            "type": "leaf",
            "state": {
              "type": "file-explorer",
              "state": {
                "sortOrder": "alphabetical"
              }
            }
          },
          {
            "id": "cb136b29e64bb609",
            "type": "leaf",
            "state": {
              "type": "search",
              "state": {
                "query": "",
                "matchingCase": false,
                "explainSearch": false,
                "collapseAll": false,
                "extraContext": false,
                "sortOrder": "alphabetical"
              }
            }
          },
          {
            "id": "2a06ecb36aee0573",
            "type": "leaf",
            "state": {
              "type": "bookmarks",
              "state": {}
            }
          }
        ]
      }
    ],
    "direction": "horizontal",
    "width": 384.5
  },
  "right": {
    "id": "4b7f478917d12190",
    "type": "split",
    "children": [
      {
        "id": "1c731ef8ebc87784",
        "type": "tabs",
        "children": [
          {
            "id": "487f3a037ccb5d24",
            "type": "leaf",
            "state": {
              "type": "backlink",
              "state": {
                "file": "6 - Full Notes/Programming/Software/Obsidian/Deploy Plugin.md",
                "collapseAll": false,
                "extraContext": false,
                "sortOrder": "alphabetical",
                "showSearch": false,
                "searchQuery": "",
                "backlinkCollapsed": false,
                "unlinkedCollapsed": true
              }
            }
          },
          {
            "id": "a8d8696f2276ac5e",
            "type": "leaf",
            "state": {
              "type": "outgoing-link",
              "state": {
                "file": "6 - Full Notes/Programming/Software/Obsidian/Deploy Plugin.md",
                "linksCollapsed": false,
                "unlinkedCollapsed": true
              }
            }
          },
          {
            "id": "29384f76e2c84c7f",
            "type": "leaf",
            "state": {
              "type": "tag",
              "state": {
                "sortOrder": "frequency",
                "useHierarchy": true
              }
            }
          },
          {
            "id": "e3cffae3db6f6dcd",
            "type": "leaf",
            "state": {
              "type": "outline",
              "state": {
                "file": "6 - Full Notes/Programming/Software/Obsidian/Deploy Plugin.md"
              }
            }
          },
          {
            "id": "5f01ef56f15bd4ac",
            "type": "leaf",
            "state": {
              "type": "markdown",
              "state": {
                "file": "6 - Full Notes/Programming/Software/Obsidian/Deploy Plugin.md",
                "mode": "source",
                "source": false
              }
            }
          },
          {
            "id": "7ec070070018b244",
            "type": "leaf",
            "state": {
              "type": "empty",
              "state": {}
            }
          },
          {
            "id": "430f5067e6a5b488",
            "type": "leaf",
            "state": {
              "type": "empty",
              "state": {}
            }
          },
          {
            "id": "fb8051bc351887f9",
            "type": "leaf",
            "state": {
              "type": "empty",
              "state": {}
            }
          },
          {
            "id": "e895a2cd4cdc9baf",
            "type": "leaf",
            "state": {
              "type": "empty",
              "state": {}
            }
          }
        ],
        "currentTab": 4
      }
    ],
    "direction": "horizontal",
    "width": 300,
    "collapsed": true
  },
  "left-ribbon": {
    "hiddenItems": {
      "note-reviewer:Open Notification Dashboard": false,
      "switcher:Open quick switcher": false,
      "graph:Open graph view": false,
      "canvas:Create new canvas": false,
      "daily-notes:Open today's daily note": false,
      "templates:Insert template": false,
      "command-palette:Open command palette": false
    }
  },
  "active": "99f0df813e2a4513",
  "lastOpenFiles": [
    "6 - Full Notes/Programming/Software/Obsidian/Deploy Plugin.md",
    "2 - Source Material/Gifs/ByteByteGo_AWS_Categories.gif",
    "6 - Full Notes/Programming/Services/Cloud/AWS/Concepts/Resources.md",
    "2 - Source Material/Gifs",
    "6 - Full Notes/Programming/Services/Cloud/AWS/Links/ByteByteGo Categories.md",
    "6 - Full Notes/Programming/Services/Cloud/AWS/Links",
    "6 - Full Notes/Programming/Services/Cloud/AWS/Services/Developer Tools/CloudFormation/CloudFormation.md",
    "6 - Full Notes/Programming/Services/Cloud/AWS/Services/Developer Tools/CloudFormation",
    "6 - Full Notes/Programming/Services/Cloud/AWS/Services/Developer Tools",
    "6 - Full Notes/Programming/Services/Cloud/AWS/Concepts/Principal.md",
    "6 - Full Notes/Programming/Services/Cloud/AWS/Services/Identity & Federation/AWS Directory Services/AWS Managed Microsoft AD/Concepts/Forest Trust.md",
    "6 - Full Notes/Programming/Services/Cloud/AWS/Services/Identity & Federation/AWS Directory Services/AWS Managed Microsoft AD/Concepts/Untitled.md",
    "6 - Full Notes/Programming/Services/Cloud/AWS/Services/Identity & Federation/AWS Directory Services/AWS Managed Microsoft AD/Connect to On-Prem AD.md",
    "6 - Full Notes/Programming/Services/Cloud/AWS/Services/Identity & Federation/AWS Directory Services/AWS Managed Microsoft AD/Concepts",
    "6 - Full Notes/Programming/Services/Cloud/AWS/Services/Identity & Federation/AWS Directory Services/AWS Managed Microsoft AD/Active Directory Replication.md",
    "6 - Full Notes/Programming/Services/Cloud/AWS/Services/Identity & Federation/AWS Directory Services/AWS Managed Microsoft AD/AWS Managed Microsoft AD.md",
    "6 - Full Notes/Programming/Concepts/Domain Join.md",
    "6 - Full Notes/Programming/Systems Design/Concepts/Concurrency vs. Parallelism.md",
    "1 - Rough Notes/Concurrency vs. Parallelism.md",
    "6 - Full Notes/Programming/Services/Cloud/AWS/Services/Compute/Lambda/Layers.md",
    "6 - Full Notes/Programming/Services/Cloud/AWS/Services/Identity & Federation/AWS Directory Services/AD Connector/AD Connector.md",
    "3 - Tags/ADR.md",
    "0 - TODO/LiftsKit.md",
    "6 - Full Notes/Programming/Frameworks/Expo/Expo.md",
    "0 - TODO/Note Reviewer.md",
    "6 - Full Notes/Private/Professional/Interviews/Companies/ServiceCore/ServiceCore - Final Interview 2.md",
    "6 - Full Notes/Private/Professional/Work History/BragSheet/John Deere/Digital Checkout.md",
    "6 - Full Notes/Private/Professional/Interviews/Companies/ServiceCore/Last Interview Experience.md",
    "6 - Full Notes/Private/Professional/Interviews/Companies/ServiceCore/Why Do You Want To Work Here.md",
    "6 - Full Notes/Private/Professional/Interviews/Companies/ServiceCore/Questions For Sean.md",
    "6 - Full Notes/Programming/Problems/LeetCode/1140. Stone Game II.md",
    "6 - Full Notes/Programming/Data Structures & Algorithms/Dynamic Programming",
    "6 - Full Notes/Private/Professional/Work History/John Deere/Projects",
    "6 - Full Notes/Private/Professional/Work History/John Deere/Concepts",
    "6 - Full Notes/Private/Professional/Work History/John Deere",
    "6 - Full Notes/Private/Work/John Deere/Concepts",
    "Pasted image 20240710200643.png",
    "Pasted image 20240710200410.png",
    "Pasted image 20240710200331.png",
    "2 - Source Material/Diagrams/Design Google Maps.png",
    "2 - Source Material/Diagrams/Design Google Maps 1.png",
    "Pasted image 20240529133154.png",
    "Pasted image 20240526092037.png"
  ]
}